tcpip/__init__.py
tcpip-1.0.dist-info/LICENSE.txt
tcpip-1.0.dist-info/METADATA
tcpip-1.0.dist-info/WHEEL
tcpip-1.0.dist-info/top_level.txt
tcpip-1.0.dist-info/RECORD
