Metadata-Version: 2.1
Name: tcpip
Version: 1.0
Summary: This package dosen't make any sense to download
Home-page: UNKNOWN
Author: prajyot
Author-email: abc@gmail.com
License: UNKNOWN
Platform: UNKNOWN
Classifier: Programming Language :: Python :: 3
Classifier: License :: OSI Approved :: MIT License
Classifier: Operating System :: OS Independent
